kaizo/plugins/hf/__init__.py
kaizo/plugins/hf/common.py
kaizo/plugins/hf/main.py
kaizo_hf-0.1.1.dist-info/licenses/LICENSE
kaizo_hf-0.1.1.dist-info/METADATA
kaizo_hf-0.1.1.dist-info/WHEEL
kaizo_hf-0.1.1.dist-info/top_level.txt
kaizo_hf-0.1.1.dist-info/RECORD
